lomosplit/__init__.py
lomosplit/__main__.py
lomosplit/image.py
lomosplit/utils.py
lomosplit-1.0.0.dist-info/LICENSE
lomosplit-1.0.0.dist-info/METADATA
lomosplit-1.0.0.dist-info/WHEEL
lomosplit-1.0.0.dist-info/top_level.txt
lomosplit-1.0.0.dist-info/RECORD
