Metadata-Version: 2.1
Name: lomosplit
Version: 1.0.0
Summary: Utility for splitting LomoKino film scans
Home-page: https://github.com/meownoid/lomosplit
Author: Egor Malykh
Author-email: fnk@fea.st
License: MIT
Platform: UNKNOWN
Requires-Dist: natsort
Requires-Dist: numpy
Requires-Dist: scikit-image
